mail2gg/__init__.py
mail2gg/cli/__init__.py
mail2gg/cli/loaders.py
mail2gg-0.1.5.dist-info/LICENSE
mail2gg-0.1.5.dist-info/METADATA
mail2gg-0.1.5.dist-info/WHEEL
mail2gg-0.1.5.dist-info/entry_points.txt
mail2gg-0.1.5.dist-info/top_level.txt
mail2gg-0.1.5.dist-info/RECORD
