Metadata-Version: 2.1
Name: mail2gg
Version: 0.1.5
Summary: Import mail to Google Groups using an IMAP account or mbox file
Home-page: https://github.com/XaviTorello/mail2gg
Author: Xavi Torelló
Author-email: info@xaviertorello.cat
License: UNKNOWN
Download-URL: https://github.com/XaviTorello/mail2gg/archive/master.zip
Project-URL: Bug Reports, https://github.com/XaviTorello/mail2gg/issues
Project-URL: Source, https://github.com/XaviTorello/mail2gg
Project-URL: Download, https://github.com/XaviTorello/mail2gg/archive/master.zip
Keywords: mail importer googlegroups google groups imap mbox migrate
Platform: UNKNOWN
Classifier: Development Status :: 4 - Beta
Classifier: License :: OSI Approved :: GNU Affero General Public License v3 or later (AGPLv3+)
Classifier: Environment :: Console
Classifier: Topic :: Communications :: Email
Classifier: Intended Audience :: End Users/Desktop
Classifier: Intended Audience :: Developers
Classifier: Intended Audience :: System Administrators
Classifier: Operating System :: POSIX
Classifier: Operating System :: POSIX :: Linux
Classifier: Operating System :: MacOS :: MacOS X
Classifier: Operating System :: Microsoft :: Windows
Classifier: Programming Language :: Python :: 3
Classifier: Programming Language :: Python :: 3.5
Classifier: Programming Language :: Python :: 3.6
Classifier: Programming Language :: Python :: 3.7
Classifier: Programming Language :: Python :: 3.8
Classifier: Programming Language :: Python :: 3.9
Classifier: Programming Language :: Python :: 3
Requires-Python: >=3.5, <4
Requires-Dist: httplib2
Requires-Dist: oauth2client
Requires-Dist: imap-tools
Requires-Dist: google-api-python-client
Requires-Dist: fire
Requires-Dist: tqdm
